qarag/__init__.py
qarag/pipe.py
ragalonepack-1.0.0.dist-info/METADATA
ragalonepack-1.0.0.dist-info/WHEEL
ragalonepack-1.0.0.dist-info/top_level.txt
ragalonepack-1.0.0.dist-info/RECORD
